videosdk/plugins/sip/__init__.py
videosdk/plugins/sip/sip.py
videosdk/plugins/sip/version.py
videosdk/plugins/sip/providers/__init__.py
videosdk/plugins/sip/providers/twilio.py
videosdk_plugins_sip-0.0.30.dist-info/METADATA
videosdk_plugins_sip-0.0.30.dist-info/WHEEL
videosdk_plugins_sip-0.0.30.dist-info/RECORD
